Workbook

Sheet Input
B2: Name: | C2: James E. Rosales
B3: Address: | C3: Purok-8 Slaughter, Obrero, Butuan City, Agusan del Norte
B4: Position: | C4: Information Systems Analyst II
B5: Salary: | C5: 35106
B6: TIN: | C6: 633-884-331-0000
B7: Entity Name: | C7: Department of Agriculture Regional Field Office XIII
B8: Fund Cluster: | C8: 1
B9: Division: | C9: Field Operations Division
B10: Official Station: | C10: Department of Agriculture Regional Field Office XIII
B11: Official Station Address: | C11: Capitol Site, Butuan City, Agusan del Norte
B12: Month | C12: September 2026
B13: Dates of Travel: | C13: Sept. 8-10, Sept. 15-17, and Sept. 22-24, 2026
B14: Travel Nos.: | C14: 0926-0573, 0926-1268, and 0926-1522
B15: Evidence of Travel: | C15: Approved Itinerary of Travel, Approved Travel Order, Bus Tickets, Certificate of Appearance
B16: FOD Chief: | C16: Melody M. Guimary
B17: RTD for Operations: | C17: Rebecca R. Atega
B18: Itinerary Total Amount: | C18: ='IT-09-P01'!K36 -> 5160
B19: Charge To: | C19: Agricultural Statistics Funds
B20: Director-In-Charge: | C20: Engr. Ricardo M. Oñate Jr.
B21: Chief of Budget Section: | C21: Fatima D. Campos
B22: Accounting Section: | C22: Jane V. Mamba
B23: Chief of Admin and Finance Division: | C23: Primitiva O. Arquion
B25: TO Departure Date: | C25: September 8, 2026
B26: TO Return Date: | C26: September 10, 2026
B27: Place of Travel | C27: Cabataña Farm, Brgy. Buena Gracia, Talacogon, Agusan del Sur
B28: Purpose: | C28: Training on Climate-Resilient Rice Production
B29: Objective: | C29: Capacitate skills with Palayamanan Plus Approach
B30: Per Diem Allowed: | C30: Yes
B31: Assistant Laborer Allowed: | C31: No

Sheet ORS
G3: Republic of the Philippines
G4: DEPARTMENT OF AGRICULTURE
G5: Caraga Region
G6: Capitol Site, Butuan City
G7: Tel. No: (085) 342-4092 Telefax No: (085) 341-2114
G8: COA Circular 2015-002: Annex F
B10: OBLIGATION REQUEST AND STATUS | L10: Serial No. : _____________________
L11: Date : _________________________
L12: ="Fund Cluster: " & Input!C8 -> Fund Cluster: 1
B13: Payee | E13: =Input!C2 -> James E. Rosales
B15: Office | E15: =Input!C10 -> Department of Agriculture Regional Field Office XIII
B17: ="FOR PAYMENT:" & CHAR(10) & CHAR(10) & "For reimbursement of travel expenses incurred during official travel from " & TEXT(Input!C13, "mmmm d, yyyy") & ", per Travel Order Nos. " & Input!C14 & ", with supporting documents hereto attached in the amount of ..." -> FOR PAYMENT: For reimbursement of travel expenses incurred during official travel from Sept. 8-10, Sept. 15-17, and Sept. 22-24, 2026, per Travel Order Nos. 0926-0573, 0926-1268, and 0926-1522, with supporting documents hereto attached in the amount of ... | E17: =Input!C11 -> Capitol Site, Butuan City, Agusan del Norte
B19: Responsibility Center | E19: Particulars | J19: MFO/PAP | L19: UACS | M19: Amount
L20: Object
L21: Code
E22: ="TO OBLIGATE:" & CHAR(10) & CHAR(10) & "Travel expenses incurred during official travel for the month of " & Input!C12 & " , pursuant to Travel Order Nos. " & Input!C14 & " dated " & TEXT(Input!C13, "mmmm d, yyyy") & " with supporting documents hereto attached in the amount of ..." & CHAR(10) & CHAR(10) & "Charged to: " & Input!C19 & "" -> TO OBLIGATE: Travel expenses incurred during official travel for the month of September 2026 , pursuant to Travel Order Nos. 0926-0573, 0926-1268, and 0926-1522 dated Sept. 8-10, Sept. 15-17, and Sept. 22-24, 2026 with supporting documents hereto attached in the amount of ... Charged to: Agricultural Statistics Funds | M22: =Input!C18 -> 5160
B28: Total | M28: =M22 -> 5160
B29: A | C29: Certified: Charges to appropriation/alloment are | J29: B | K29: Certified: Allotment available and obligated
C30: necessary, lawful and under my direct supervision; | K30: for the purpose/adjustment necessary as
C31: and supporting documents valid, proper and legal | K31: indicated above
B35: Signature : | J35: Signature :
B36: Printed Name : | D36: =UPPER(Input!C16) -> MELODY M. GUIMARY | J36: Printed Name : | L36: =UPPER(Input!C21) -> FATIMA D. CAMPOS
B37: Position : | D37: Chief, Field Operations Division | J37: Position : | L37: Chief, Budget Section
B38: Date : | J38: Date :
B40: C | C40: STATUS OF OBLIGATION
B41: Reference | I41: Amount
B42: Date | C42: Particulars | F42: ORS/JEV/Check/ ADA/TRA No. | I42: Obligation | J42: Payable | L42: Payment | M42: Balance
M43: Not Yet Due | N43: Due and Demandable
I45: (a) | J45: (b) | L45: (c) | M45: (a-b) | N45: (b-c)

Sheet DV 
AC2: Appendix 32
B3: Republic of the Philippines | AC3: Fund Cluster :
B4: DEPARTMENT OF AGRICULTURE | AC4: =Input!C8 -> 1
B5: Caraga Region | AC5: Date :
B6: Capitol Site, Butuan City
B7: Tel. No: (085) 342-4092 Telefax No: (085) 341-2114 | AC7: DV No. :
B9: DISBURSEMENT VOUCHER
B11: Mode of Payment
I12: MDS Check | O12: Commercial Check | T12: ADA | Z12: Others (Please specify) ____________________
B14: Payee | F14: =Input!C2 -> James E. Rosales | T14: TIN/Employee No.: | AC14: ORS/BURS No.:
T15: =Input!C6 -> 633-884-331-0000
B16: Address | F16: =Input!C3 -> Purok-8 Slaughter, Obrero, Butuan City, Agusan del Norte
B18: Particulars | S18: Responsibility Center | X18: MFO/PAP | AC18: Amount
B19: ="FOR PAYMENT:" & CHAR(10) & CHAR(10) & "For reimbursement of travel expenses incurred during official travel from " & TEXT(Input!C13, "mmmm d, yyyy") & " per Travel Order Nos. " & Input!C14 & ", with supporting documents hereto attached in the amount of ..." -> FOR PAYMENT: For reimbursement of travel expenses incurred during official travel from Sept. 8-10, Sept. 15-17, and Sept. 22-24, 2026 per Travel Order Nos. 0926-0573, 0926-1268, and 0926-1522, with supporting documents hereto attached in the amount of ... | AC19: =Input!C18 -> 5160
B24: Amount Due | AC24: =AC19 -> 5160
B25: A. | C25: Certified: Expenses/Cash Advance necessary, lawful and incurred under my direct supervision.
B28: =UPPER(Input!C16) -> MELODY M. GUIMARY
B29: Chief, Field Operations Division
B31: B. | C31: Accounting Entry:
B32: Account Title | S32: UACS Code | AA32: Debit | AG32: Credit
B34: C. | C34: Certified: | T34: D. | U34: Approved for Payment
D36: Cash available
D38: Subject to Authority to Debit Account (when applicable)
D40: Supporting documents complete and amount claimed | E40: Supporting documents complete and amount claimed | T40: (₱ )
D41: proper | T41: (Amount in words and in figure)
B43: Signature | T43: Signature
B45: Printed Name | F45: =UPPER(Input!C22) -> JANE V. MAMBA | T45: Printed Name | X45: =UPPER(Input!C23) -> PRIMITIVA O. ARQUION
B47: Position | F47: Accounting Section | T47: Position | X47: Chief, Admin and Finance Division
F48: Head, Accounting Unit/Authorized Representative | X48: Agency Head/Authorized Representative
B49: Date | T49: Date
B51: E. | C51: Receipt of Payment | AC51: JEV No.
B52: Check/ ADA No. : | O52: Date : | T52: Bank Name & Account Number:
B54: Signature : | O54: Date : | T54: Printed Name: | AC54: Date
B56: Official Receipt No. & Date/Other Documents:

Sheet IT-09-P01
B2: Republic of the Philippines
B3: DEPARTMENT OF AGRICULTURE
B4: Caraga Region
B5: Capitol Site, Butuan City
B6: Tel. No: (085) 342-4092 Telefax No: (085) 341-2114
I7: Appendix 45
B8: ITINERARY OF TRAVEL
B10: Entity Name : | C10: =Input!C7 -> Department of Agriculture Regional Field Office XIII
B11: Fund Cluster : | C11: =Input!C8 -> 1 | I11: No.:
B13: Name : | C13: =Input!C2 -> James E. Rosales | F13: Date of Travel : | H13: =Input!C13 -> Sept. 8-10, Sept. 15-17, and Sept. 22-24, 2026
B14: Position : | C14: =Input!C4 -> Information Systems Analyst II | F14: Purpose of Travel : | H14: Please see attached Travel Orders
B15: Official Station : | C15: =Input!C10 -> Department of Agriculture Regional Field Office XIII
B16: Date | C16: Places to be visited | E16: T I M E | G16: Means of | H16: Transportation | I16: Per | J16: Others | K16: Total Amount
C17: (Destination) | E17: Departure | F17: Arrival | G17: Transportation | I17: Diem
B18: September 8, 2026 | C18: OS to Cabataña Farm, Brgy. Buena Gracia, Talacogon, Agusan del Sur | E18: 0.20833333 | F18: 0.3125 | G18: RP | I18: 1050 | K18: =SUM(H18:J18) -> 1050
B19: September 9, 2026 | C19: Still at Talacogon, Agusan del Sur | E19: 0.33333333 | F19: 0.70833333 | I19: 1050 | K19: =SUM(H19:J19) -> 1050
B20: September 10, 2026 | C20: Cabataña Farm, Brgy. Buena Gracia, Talacogon, Agusan del Sur to Talacogon Bus Terminal | E20: 0.70833333 | F20: 0.71875 | G20: MCH | H20: 50 | K20: =SUM(H20:J20) -> 50
C21: Talacogon Bus Terminal to Butuan City Bus Terminal | E21: =F20 -> 0.71875 | F21: 0.82291667 | G21: PUB | H21: 280 | K21: =SUM(H21:J21) -> 280
C22: Butuan City Bus Terminal to OS | E22: =F21 -> 0.82291667 | F22: 0.83333333 | G22: MCH | H22: 30 | I22: 450 | K22: =SUM(H22:J22) -> 480
B23: September 15, 2026 | C23: OS to Shacene Pension House and Restaurant, Brgy. Mabua, Tandag City, Surigao del Sur | E23: 0.20833333 | F23: 0.41666667 | G23: RP | I23: 450 | K23: =SUM(H23:J23) -> 450
B24: September 16, 2026 | C24: Still at Shacene Pension House and Restaurant, Brgy. Mabua, Tandag City, Surigao del Sur | E24: 0.33333333 | F24: 0.70833333 | I24: 300 | K24: =SUM(H24:J24) -> 300
B25: September 17, 2026 | C25: Shacene Pension House and Restaurant, Brgy. Mabua, Tandag City, Surigao del Sur to OS | E25: =F24 -> 0.70833333 | F25: 0.91666667 | G25: RP | I25: 450 | K25: =SUM(H25:J25) -> 450
B26: September 22, 2026 | C26: OS to Development of Agusanons, Inc., Patin-ay, Prosperidad, Agusan del Sur | E26: 0.33333333 | F26: 0.41666667 | G26: RP | I26: 300 | K26: =SUM(H26:J26) -> 300
B27: September 23, 2026 | C27: Still at Development of Agusanons, Inc., Patin-ay, Prosperidad, Agusan del Sur | E27: 0.33333333 | F27: 0.70833333 | I27: 300 | K27: =SUM(H27:J27) -> 300
B28: September 24, 2026 | C28: Development of Agusanons, Inc., Patin-ay, Prosperidad, Agusan del Sur to OS | E28: =F26 -> 0.41666667 | F28: 0.79166667 | G28: RP | I28: 450 | K28: =SUM(H28:J28) -> 450
B36: TOTAL | H36: =SUM(H18:H35) -> 360 | I36: =SUM(I18:I35) -> 4800 | J36: =SUM(J18:J35) -> 0 | K36: =SUM(H36:J36) -> 5160
B38: I certify that: (1) I have reviewed the foregoing itinerary; (2) the travel is necessary to the service; (3) the period covered is reasonable; and (4) the expenses claimed are proper. | F38: Prepared:
F41: =UPPER(Input!C2) -> JAMES E. ROSALES
F42: =Input!C4 -> Information Systems Analyst II
F43: Approved:
B46: =UPPER(Input!C16) -> MELODY M. GUIMARY | F46: =UPPER(Input!C17) -> REBECCA R. ATEGA
B47: Chief, Field Operations Division | F47: RTD for Operations

Sheet CTC
B2: Appendix 47
B4: CERTIFICATION OF TRAVEL COMPLETED
B7: Entity Name: | D7: =Input!C7 -> Department of Agriculture Regional Field Office XIII | I7: Fund Cluster: | J7: =Input!C8 -> 1
B11: =UPPER(Input!C20) -> ENGR. RICARDO M. OÑATE JR. | F11: =UPPER(Input!C9) -> FIELD OPERATIONS DIVISION
B12: Director-In-Charge | F12: Station
B15: ="I HEREBY CERTIFY THAT I have completed the travel as authorized in Travel Order/Itinerary of Travel Nos. " & Input!C14 & ", dated " & TEXT(Input!C13, "mmmm d, yyyy") & " under the conditions indicated below:" -> I HEREBY CERTIFY THAT I have completed the travel as authorized in Travel Order/Itinerary of Travel Nos. 0926-0573, 0926-1268, and 0926-1522, dated Sept. 8-10, Sept. 15-17, and Sept. 22-24, 2026 under the conditions indicated below:
B19: Strictly in accordance with the approved itinerary.
B20: Cut short as explained below. Excess payment in the amount of
B21: ₱ _______ was refunded under O. R. No. ______________ dated ________________.
B22: Extended as explained below, additional itinerary was submitted.
B23: Other deviation as explained below.
B25: Explanation or Justification:
B29: Evidence of Travel:
B30: =Input!C15 -> Approved Itinerary of Travel, Approved Travel Order, Bus Tickets, Certificate of Appearance
G32: Respectfully submitted:
B36: =UPPER(Input!C2) -> JAMES E. ROSALES
B37: Name of Employee
B38: On evidence and information of which I have the knowledge, the travel was actually undertaken.
G44: Noted:
B48: =UPPER(Input!C16) -> MELODY M. GUIMARY
B49: Chief, Field Operations Division

Sheet COENRR
B3: Republic of the Philippines
B4: DEPARTMENT OF AGRICULTURE
B5: Caraga Region
B6: Capitol Site, Butuan City
B7: Tel. No: (085) 342-4092 Telefax No: (085) 341-2114
B9: CERTIFICATION OF EXPENSES NOT REQUIRING RECEIPTS
B11: Pursuant to COA Circular No. 2017-001 dated June 19, 2017
B13: Name of Employee: | D13: =Input!C2 -> James E. Rosales | G13: Employee No. | I13: =Input!C6 -> 633-884-331-0000
B14: Office: | D14: =Input!C10 -> Department of Agriculture Regional Field Office XIII
B15: Division: | D15: =(Input!C9) -> Field Operations Division
B17: DATE | D17: PARTICULARS | G17: MEANS OF TRANSPORTATION | I17: AMOUNT
B18: September 10, 2026 | D18: Cabataña Farm, Brgy. Buena Gracia, Talacogon, Agusan del Sur to Talacogon Bus Terminal | G18: MCH | I18: 50
D19: Butuan City Bus Terminal to OS | G19: MCH | I19: 30
B46: Total | I46: =SUM(I18:K45) -> 80
B47: Purpose: Please see attached Travel Orders.
B48: I hereby certify that the above expenses are incurred as they are necessary for the above cited purpose, that above goods and services were acquired from parties not issuing receipts. And that I am fully aware that willful falsification of statements is punishable by law.
D49: Certified Correct: | G49: Noted:
B50: Signature
B51: Printed Name | D51: =UPPER(Input!C2) -> JAMES E. ROSALES | G51: =UPPER(Input!C16) -> MELODY M. GUIMARY
D52: Employee | G52: Immediate Supervisor
D53: Date | G53: Date

Sheet PTR Checklist
B2: No. | C2: Travel Date | D2: Darfted | E2: Submitted | F2: Approved
B3: 1 | C3: September 8-10, 2026 | D3: Yes | E3: - | F3: -
B4: 2
B5: 3
B6: 4
B7: 5
B8: 6
B9: 7
B10: 8
B11: 9
B12: 10
B13: 11
B14: 12
B15: 13
... B26: 24

Sheet Travel Order
B4: Republic of the Philippines
B5: DEPARTMENT OF AGRICULTURE
B6: Caraga Region
B7: Capitol Site, Butuan City
B8: Tel. No: (085) 342-4092 Telefax No.: (085) 341-2114
B11: TRAVEL ORDER
Y16: No.:
Y17: Date:
C19: Name: | G19: =Input!C2 -> James E. Rosales | R19: Salary Per Month: | X19: =Input!C5 -> 35106
C20: Position: | G20: =Input!C4 -> Information Systems Analyst II | R20: Office Station: | X20: DA-RFO XIII
C22: Departure Date : | J22: =Input!C25 -> September 8, 2026 | R22: Return Date: | X22: =Input!C26 -> September 10, 2026
C24: Place of Travel: | J24: =Input!C27 -> Cabataña Farm, Brgy. Buena Gracia, Talacogon, Agusan del Sur
C26: Specific Purpose of the Trip: | N26: =Input!C28 -> Training on Climate-Resilient Rice Production
C29: Objectives: | K29: =Input!C29 -> Capacitate skills with Palayamanan Plus Approach
C31: Per Diems Allowed: | K31: =Input!C30 -> Yes
C33: Assistant Laborers Allowed: | N33: =Input!C31 -> No
C35: Appropriation to which travel should be charged: | U35: =Input!C19 -> Agricultural Statistics Funds
C37: Remarks or Special Instructions:
C39: Recommending Approval: | V39: Approved:
D42: =UPPER(Input!C17) -> REBECCA R. ATEGA | V42: =UPPER(Input!C20) -> ENGR. RICARDO M. OÑATE JR.
D43: RTD for Operations | V43: Regional Executive Director
B45: Date | H45: Place of visited | AA45: Certifying Officer
